<RenderPhase>
	<RenderTarget flag="1"/>
	<RenderQueue materialid="6" materialname="material/indirectlightmap.xml" for="IndirectLightMap">
		<PhaseQuote id="1">
			<TextureUniform name="tRSMFlux" slot="4" flag="1"/>
			<TextureUniform name="tRSMPosition" slot="5" flag="2"/>
			<TextureUniform name="tRSMNormal" slot="6" flag="4"/>
		</PhaseQuote>
		<PhaseQuote id="3">
			<TextureUniform name="tGColor" slot="0" flag="1"/>
			<TextureUniform name="tGPosition" slot="1" flag="2"/>
			<TextureUniform name="tGNormal" slot="2" flag="4"/>
		</PhaseQuote>
	</RenderQueue>
</RenderPhase>